sleepcount.py
sleepcount-0.2.1.dist-info/METADATA
sleepcount-0.2.1.dist-info/WHEEL
sleepcount-0.2.1.dist-info/entry_points.txt
sleepcount-0.2.1.dist-info/licenses/LICENSE
sleepcount-0.2.1.dist-info/RECORD
